dq_db_manager/__init__.py
dq_db_manager/database_factory.py
dq_db_manager/main.py
dq_db_manager/handlers/__init__.py
dq_db_manager/handlers/amazons3/__init__.py
dq_db_manager/handlers/amazons3/s3_client_handler.py
dq_db_manager/handlers/amazons3/s3_connection_details_parser.py
dq_db_manager/handlers/amazons3/s3_connection_handler.py
dq_db_manager/handlers/amazons3/s3_metadata_extractor.py
dq_db_manager/handlers/base/__init__.py
dq_db_manager/handlers/base/connection_handler.py
dq_db_manager/handlers/base/db_handler.py
dq_db_manager/handlers/base/metadata_extractor.py
dq_db_manager/handlers/cockroach/__init__.py
dq_db_manager/handlers/cockroach/db_handler.py
dq_db_manager/handlers/maria/__init__.py
dq_db_manager/handlers/maria/connection_details_parser.py
dq_db_manager/handlers/maria/connection_handler.py
dq_db_manager/handlers/maria/db_handler.py
dq_db_manager/handlers/maria/metadata_extractor.py
dq_db_manager/handlers/mysql/__init__.py
dq_db_manager/handlers/mysql/db_handler.py
dq_db_manager/handlers/oracle/__init__.py
dq_db_manager/handlers/oracle/connection_details_parser.py
dq_db_manager/handlers/oracle/connection_handler.py
dq_db_manager/handlers/oracle/db_handler.py
dq_db_manager/handlers/oracle/metadata_extractor.py
dq_db_manager/handlers/postgresql/__init__.py
dq_db_manager/handlers/postgresql/connection_details_parser.py
dq_db_manager/handlers/postgresql/connection_handler.py
dq_db_manager/handlers/postgresql/db_handler.py
dq_db_manager/handlers/postgresql/metadata_extractor.py
dq_db_manager/handlers/sqlite/__init__.py
dq_db_manager/handlers/sqlite/connection_details_parser.py
dq_db_manager/handlers/sqlite/connection_handler.py
dq_db_manager/handlers/sqlite/db_handler.py
dq_db_manager/handlers/sqlite/metadata_extractor.py
dq_db_manager/handlers/vertica/__init__.py
dq_db_manager/handlers/vertica/connection_details_parser.py
dq_db_manager/handlers/vertica/connection_handler.py
dq_db_manager/handlers/vertica/db_handler.py
dq_db_manager-0.2.0.dist-info/licenses/AUTHORS.rst
dq_db_manager-0.2.0.dist-info/licenses/LICENSE
dq_db_manager-0.2.0.dist-info/METADATA
dq_db_manager-0.2.0.dist-info/WHEEL
dq_db_manager-0.2.0.dist-info/top_level.txt
dq_db_manager-0.2.0.dist-info/RECORD
